lib/counter.v
module counter # (
	parameter WIDTH = 16
) (
	input clk,
	input rst_n,
	output reg [WIDTH-1:0] cnt
);

always @(posedge clk) begin
	if (rst_n == 0)
		cnt <= {WIDTH{1'b0}};
	else
		cnt <= cnt + 1;
end

endmodule

rotate.v
module wash_fsm # (
    parameter CNTW = 6,      // count width
    parameter SW = 3,       // state width
    parameter MW = 2,       // motor width
    parameter CW = 32,
    parameter CCW = 32,
    parameter PAUSE = 16,
    parameter S0 = 0,
    parameter S1 = 1,
    parameter S2 = 2,
    parameter S3 = 3,
    parameter S4 = 4,
    parameter M0 = 0,
    parameter M1 = 1,
    parameter M2 = 2
) (
    input clk,		// 1Hz
    input rst_n,
    // 0 for stop, 1 for clockwise, 2 for counterclockwise, 3 undefined
    output [1:0] motor,
    // 0 for stopping, 1 for working
    // negedge indicate completion
    output compl_n
);

wire [CNTW-1:0] cnt;
reg [SW-1:0] state;
wire [SW-1:0] next;
wire clear;
reg clear_reg;

counter #(.WIDTH(CNTW))    c0	(	.clk(clk),
			                        .rst_n(clear),
			                        .cnt(cnt));

assign motor = {SW{rst_n}} &   (state == S1 ? M1 :
                                state == S2 ? M0 :
                                state == S3 ? M2 :
                                state == S4 ? M0 : M0);

assign clear = rst_n & over;

assign next =  (state == S1 && cnt == CW    ? S2 :
                state == S2 && cnt == PAUSE ? S3 :
                state == S3 && cnt == CCW   ? S4 :
                state == S4 && cnt == PAUSE ? S0 : state);

assign over =  (state == S1 && cnt == CW    ? 0 :
                state == S2 && cnt == PAUSE ? 0 :
                state == S3 && cnt == CCW   ? 0 :
                state == S4 && cnt == PAUSE ? 0 : 1);

assign compl_n = (state != S0);

always@(posedge clk) begin
    if (~rst_n)
        state <= S1;
    else
        state <= next;
end

endmodule

rotate_tb.v
`timescale 1s/1us

module wash_fsm_tb;
    parameter WIDTH     = 16;
    parameter FREQ      = 8;
    parameter PERIOD    = 30;

    reg     clk;    // 40kHz
    reg     rst_n;
	wire 	[1:0]	motor;
	wire 	compl_n;

    wash_fsm c0 (	.clk(clk),
		 		   	.rst_n(rst_n),
					.motor(motor),
					.compl_n(compl_n));


    initial begin            
        $dumpfile("wash_fsm.vcd");
        $dumpvars(0, wash_fsm_tb);
    end

    always #(0.5 / FREQ)
        clk     <= ~clk;

    initial begin
        clk		<= 1'b1;

        rst_n	<= 1'b0;
        #(2) rst_n	<= 1'b1;

        #(15) rst_n <= 1'b0;
        #(16) rst_n <= 1'b1;

        #PERIOD $finish;
    end

endmodule

rotate.vcd
$date
	Mon Mar  7 08:06:34 2022
$end
$version
	Icarus Verilog
$end
$timescale
	1us
$end
$scope module wash_fsm_tb $end
$var wire 2 ! motor [1:0] $end
$var wire 1 " compl_n $end
$var reg 1 # clk $end
$var reg 1 $ rst_n $end
$scope module c0 $end
$var wire 1 % clear $end
$var wire 1 # clk $end
$var wire 1 $ rst_n $end
$var wire 1 & over $end
$var wire 3 ' next [2:0] $end
$var wire 2 ( motor [1:0] $end
$var wire 1 " compl_n $end
$var wire 6 ) cnt [5:0] $end
$var reg 3 * state [2:0] $end
$scope module c0 $end
$var wire 1 # clk $end
$var wire 1 % rst_n $end
$var reg 6 + cnt [5:0] $end
$upscope $end
$upscope $end
$upscope $end
$enddefinitions $end
#0
$dumpvars
bx +
b1 *
bx )
b0 (
b0xx '
x&
0%
0$
1#
1"
b0 !
$end
#62500
0#
#125000
1&
b1 '
b0 )
b0 +
1#
#187500
0#
#250000
1#
#312500
0#
#375000
1#
#437500
0#
#500000
1#
#562500
0#
#625000
1#
#687500
0#
#750000
1#
#812500
0#
#875000
1#
#937500
0#
#1000000
1#
#1062500
0#
#1125000
1#
#1187500
0#
#1250000
1#
#1312500
0#
#1375000
1#
#1437500
0#
#1500000
1#
#1562500
0#
#1625000
1#
#1687500
0#
#1750000
1#
#1812500
0#
#1875000
1#
#1937500
0#
#2000000
b1 )
b1 +
b1 !
b1 (
1%
1#
1$
#2062500
0#
#2125000
b10 )
b10 +
1#
#2187500
0#
#2250000
b11 )
b11 +
1#
#2312500
0#
#2375000
b100 )
b100 +
1#
#2437500
0#
#2500000
b101 )
b101 +
1#
#2562500
0#
#2625000
b110 )
b110 +
1#
#2687500
0#
#2750000
b111 )
b111 +
1#
#2812500
0#
#2875000
b1000 )
b1000 +
1#
#2937500
0#
#3000000
b1001 )
b1001 +
1#
#3062500
0#
#3125000
b1010 )
b1010 +
1#
#3187500
0#
#3250000
b1011 )
b1011 +
1#
#3312500
0#
#3375000
b1100 )
b1100 +
1#
#3437500
0#
#3500000
b1101 )
b1101 +
1#
#3562500
0#
#3625000
b1110 )
b1110 +
1#
#3687500
0#
#3750000
b1111 )
b1111 +
1#
#3812500
0#
#3875000
b10000 )
b10000 +
1#
#3937500
0#
#4000000
b10001 )
b10001 +
1#
#4062500
0#
#4125000
b10010 )
b10010 +
1#
#4187500
0#
#4250000
b10011 )
b10011 +
1#
#4312500
0#
#4375000
b10100 )
b10100 +
1#
#4437500
0#
#4500000
b10101 )
b10101 +
1#
#4562500
0#
#4625000
b10110 )
b10110 +
1#
#4687500
0#
#4750000
b10111 )
b10111 +
1#
#4812500
0#
#4875000
b11000 )
b11000 +
1#
#4937500
0#
#5000000
b11001 )
b11001 +
1#
#5062500
0#
#5125000
b11010 )
b11010 +
1#
#5187500
0#
#5250000
b11011 )
b11011 +
1#
#5312500
0#
#5375000
b11100 )
b11100 +
1#
#5437500
0#
#5500000
b11101 )
b11101 +
1#
#5562500
0#
#5625000
b11110 )
b11110 +
1#
#5687500
0#
#5750000
b11111 )
b11111 +
1#
#5812500
0#
#5875000
0%
0&
b10 '
b100000 )
b100000 +
1#
#5937500
0#
#6000000
1%
b0 !
b0 (
b10 '
1&
b0 )
b0 +
b10 *
1#
#6062500
0#
#6125000
b1 )
b1 +
1#
#6187500
0#
#6250000
b10 )
b10 +
1#
#6312500
0#
#6375000
b11 )
b11 +
1#
#6437500
0#
#6500000
b100 )
b100 +
1#
#6562500
0#
#6625000
b101 )
b101 +
1#
#6687500
0#
#6750000
b110 )
b110 +
1#
#6812500
0#
#6875000
b111 )
b111 +
1#
#6937500
0#
#7000000
b1000 )
b1000 +
1#
#7062500
0#
#7125000
b1001 )
b1001 +
1#
#7187500
0#
#7250000
b1010 )
b1010 +
1#
#7312500
0#
#7375000
b1011 )
b1011 +
1#
#7437500
0#
#7500000
b1100 )
b1100 +
1#
#7562500
0#
#7625000
b1101 )
b1101 +
1#
#7687500
0#
#7750000
b1110 )
b1110 +
1#
#7812500
0#
#7875000
b1111 )
b1111 +
1#
#7937500
0#
#8000000
0%
0&
b11 '
b10000 )
b10000 +
1#
#8062500
0#
#8125000
1%
b10 !
b10 (
1&
b11 '
b11 *
b0 )
b0 +
1#
#8187500
0#
#8250000
b1 )
b1 +
1#
#8312500
0#
#8375000
b10 )
b10 +
1#
#8437500
0#
#8500000
b11 )
b11 +
1#
#8562500
0#
#8625000
b100 )
b100 +
1#
#8687500
0#
#8750000
b101 )
b101 +
1#
#8812500
0#
#8875000
b110 )
b110 +
1#
#8937500
0#
#9000000
b111 )
b111 +
1#
#9062500
0#
#9125000
b1000 )
b1000 +
1#
#9187500
0#
#9250000
b1001 )
b1001 +
1#
#9312500
0#
#9375000
b1010 )
b1010 +
1#
#9437500
0#
#9500000
b1011 )
b1011 +
1#
#9562500
0#
#9625000
b1100 )
b1100 +
1#
#9687500
0#
#9750000
b1101 )
b1101 +
1#
#9812500
0#
#9875000
b1110 )
b1110 +
1#
#9937500
0#
#10000000
b1111 )
b1111 +
1#
#10062500
0#
#10125000
b10000 )
b10000 +
1#
#10187500
0#
#10250000
b10001 )
b10001 +
1#
#10312500
0#
#10375000
b10010 )
b10010 +
1#
#10437500
0#
#10500000
b10011 )
b10011 +
1#
#10562500
0#
#10625000
b10100 )
b10100 +
1#
#10687500
0#
#10750000
b10101 )
b10101 +
1#
#10812500
0#
#10875000
b10110 )
b10110 +
1#
#10937500
0#
#11000000
b10111 )
b10111 +
1#
#11062500
0#
#11125000
b11000 )
b11000 +
1#
#11187500
0#
#11250000
b11001 )
b11001 +
1#
#11312500
0#
#11375000
b11010 )
b11010 +
1#
#11437500
0#
#11500000
b11011 )
b11011 +
1#
#11562500
0#
#11625000
b11100 )
b11100 +
1#
#11687500
0#
#11750000
b11101 )
b11101 +
1#
#11812500
0#
#11875000
b11110 )
b11110 +
1#
#11937500
0#
#12000000
b11111 )
b11111 +
1#
#12062500
0#
#12125000
0%
0&
b100 '
b100000 )
b100000 +
1#
#12187500
0#
#12250000
1%
b0 !
b0 (
1&
b0 )
b0 +
b100 *
1#
#12312500
0#
#12375000
b1 )
b1 +
1#
#12437500
0#
#12500000
b10 )
b10 +
1#
#12562500
0#
#12625000
b11 )
b11 +
1#
#12687500
0#
#12750000
b100 )
b100 +
1#
#12812500
0#
#12875000
b101 )
b101 +
1#
#12937500
0#
#13000000
b110 )
b110 +
1#
#13062500
0#
#13125000
b111 )
b111 +
1#
#13187500
0#
#13250000
b1000 )
b1000 +
1#
#13312500
0#
#13375000
b1001 )
b1001 +
1#
#13437500
0#
#13500000
b1010 )
b1010 +
1#
#13562500
0#
#13625000
b1011 )
b1011 +
1#
#13687500
0#
#13750000
b1100 )
b1100 +
1#
#13812500
0#
#13875000
b1101 )
b1101 +
1#
#13937500
0#
#14000000
b1110 )
b1110 +
1#
#14062500
0#
#14125000
b1111 )
b1111 +
1#
#14187500
0#
#14250000
0%
0&
b0 '
b10000 )
b10000 +
1#
#14312500
0#
#14375000
1%
1&
0"
b0 *
b0 )
b0 +
1#
#14437500
0#
#14500000
b1 )
b1 +
1#
#14562500
0#
#14625000
b10 )
b10 +
1#
#14687500
0#
#14750000
b11 )
b11 +
1#
#14812500
0#
#14875000
b100 )
b100 +
1#
#14937500
0#
#15000000
b101 )
b101 +
1#
#15062500
0#
#15125000
b110 )
b110 +
1#
#15187500
0#
#15250000
b111 )
b111 +
1#
#15312500
0#
#15375000
b1000 )
b1000 +
1#
#15437500
0#
#15500000
b1001 )
b1001 +
1#
#15562500
0#
#15625000
b1010 )
b1010 +
1#
#15687500
0#
#15750000
b1011 )
b1011 +
1#
#15812500
0#
#15875000
b1100 )
b1100 +
1#
#15937500
0#
#16000000
b1101 )
b1101 +
1#
#16062500
0#
#16125000
b1110 )
b1110 +
1#
#16187500
0#
#16250000
b1111 )
b1111 +
1#
#16312500
0#
#16375000
b10000 )
b10000 +
1#
#16437500
0#
#16500000
b10001 )
b10001 +
1#
#16562500
0#
#16625000
b10010 )
b10010 +
1#
#16687500
0#
#16750000
b10011 )
b10011 +
1#
#16812500
0#
#16875000
b10100 )
b10100 +
1#
#16937500
0#
#17000000
b1 '
b0 )
b0 +
1"
b1 *
0%
1#
0$
