regfile/regfile.v
`include "regfile.h"

module regfile (
	input	wire			clk,
	input	wire			reset_,

	input	wire [`AddrBus] addr,
	input	wire [`DataBus]	d_in,
	input	wire			we_,
	output	wire [`DataBus] d_out
);

	reg [`DataBus]			ff [`DATA_D-1:0];
	integer					i;

	assign d_out = ff[addr];

	always @(posedge clk or negedge reset_) begin
		if (reset_ == `ENABLE_) begin
			for (i = 0; i < `DATA_D; i = i + 1) begin
				ff[i]	 <= #1 {`DATA_W{1'b0}};
			end
		end else begin
			if (we_ == `ENABLE_) begin
				ff[addr] <= #1 d_in;
			end
		end
	end

endmodule

regfile/regfile_test.v
`timescale 1ns/1ps

`include "regfile.h"

module regfile_test;
	reg				clk;
	reg				reset_;

	reg  [`AddrBus]	addr;
	reg  [`DataBus] d_in;
	reg				we_;
	wire [`DataBus] d_out;

	integer			i;
	parameter		STEP = 100.0000;	// 10 M


	always #(STEP / 2) begin
		clk <= ~clk;
	end

	regfile regfile (
		.clk	(clk),
		.reset_	(reset_),

		.addr	(addr),
		.d_in	(d_in),
		.we_	(we_),
		.d_out	(d_out)
	);

	initial begin
		# 0 begin
			clk		<= `HIGH;
			reset_	<= `ENABLE_;
			addr	<= {`ADDR_W{1'b0}};
			d_in	<= {`DATA_W{1'b0}};
			we_		<= `DISABLE_;
		end
		# (STEP * 3 / 4)
		# STEP begin
			reset_ <= `DISABLE_;
		end
		# STEP begin
			for (i = 0; i < `DATA_D; i = i + 1) begin
				# STEP begin
					addr	<= i;
					d_in	<= i;
					we_		<= `ENABLE_;
				end
				# STEP begin
					addr	<= {`ADDR_W{1'b0}};
					d_in	<= {`DATA_W{1'b0}};
					we_		<= `DISABLE_;
					if (d_out == i) begin
						$display($time, " ff[%d] Read/Write Check OK !", i);
					end else begin
						$display($time, " ff[%d] Read/Write Check NG !", i);
					end
				end
			end
		end	
		# STEP begin
			$finish;
		end
	end

	initial begin
		$dumpfile("regfile.vcd");
		$dumpvars(0, regfile);
	end

endmodule

regfile/regfile.vcd
$date
	Sat Nov 14 15:06:33 2020
$end
$version
	Icarus Verilog
$end
$timescale
	1ps
$end
$scope module regfile_test $end
$scope module regfile $end
$var wire 5 ! addr [4:0] $end
$var wire 1 " clk $end
$var wire 32 # d_in [31:0] $end
$var wire 32 $ d_out [31:0] $end
$var wire 1 % reset_ $end
$var wire 1 & we_ $end
$var integer 32 ' i [31:0] $end
$upscope $end
$upscope $end
$enddefinitions $end
#0
$dumpvars
b100000 '
1&
0%
bx $
b0 #
1"
b0 !
$end
#1000
b0 $
#50000
0"
#100000
b100000 '
1"
#150000
0"
#175000
1%
#200000
1"
#250000
0"
#300000
1"
#350000
0"
#375000
0&
#400000
1"
#450000
0"
#475000
1&
#500000
1"
#550000
0"
#575000
0&
b1 #
b1 !
#600000
1"
#601000
b1 $
#650000
0"
#675000
1&
b0 #
b0 $
b0 !
#700000
1"
#750000
0"
#775000
0&
b10 #
b10 !
#800000
1"
#801000
b10 $
#850000
0"
#875000
1&
b0 #
b0 $
b0 !
#900000
1"
#950000
0"
#975000
0&
b11 #
b11 !
#1000000
1"
#1001000
b11 $
#1050000
0"
#1075000
1&
b0 #
b0 $
b0 !
#1100000
1"
#1150000
0"
#1175000
0&
b100 #
b100 !
#1200000
1"
#1201000
b100 $
#1250000
0"
#1275000
1&
b0 #
b0 $
b0 !
#1300000
1"
#1350000
0"
#1375000
0&
b101 #
b101 !
#1400000
1"
#1401000
b101 $
#1450000
0"
#1475000
1&
b0 #
b0 $
b0 !
#1500000
1"
#1550000
0"
#1575000
0&
b110 #
b110 !
#1600000
1"
#1601000
b110 $
#1650000
0"
#1675000
1&
b0 #
b0 $
b0 !
#1700000
1"
#1750000
0"
#1775000
0&
b111 #
b111 !
#1800000
1"
#1801000
b111 $
#1850000
0"
#1875000
1&
b0 #
b0 $
b0 !
#1900000
1"
#1950000
0"
#1975000
0&
b1000 #
b1000 !
#2000000
1"
#2001000
b1000 $
#2050000
0"
#2075000
1&
b0 #
b0 $
b0 !
#2100000
1"
#2150000
0"
#2175000
0&
b1001 #
b1001 !
#2200000
1"
#2201000
b1001 $
#2250000
0"
#2275000
1&
b0 #
b0 $
b0 !
#2300000
1"
#2350000
0"
#2375000
0&
b1010 #
b1010 !
#2400000
1"
#2401000
b1010 $
#2450000
0"
#2475000
1&
b0 #
b0 $
b0 !
#2500000
1"
#2550000
0"
#2575000
0&
b1011 #
b1011 !
#2600000
1"
#2601000
b1011 $
#2650000
0"
#2675000
1&
b0 #
b0 $
b0 !
#2700000
1"
#2750000
0"
#2775000
0&
b1100 #
b1100 !
#2800000
1"
#2801000
b1100 $
#2850000
0"
#2875000
1&
b0 #
b0 $
b0 !
#2900000
1"
#2950000
0"
#2975000
0&
b1101 #
b1101 !
#3000000
1"
#3001000
b1101 $
#3050000
0"
#3075000
1&
b0 #
b0 $
b0 !
#3100000
1"
#3150000
0"
#3175000
0&
b1110 #
b1110 !
#3200000
1"
#3201000
b1110 $
#3250000
0"
#3275000
1&
b0 #
b0 $
b0 !
#3300000
1"
#3350000
0"
#3375000
0&
b1111 #
b1111 !
#3400000
1"
#3401000
b1111 $
#3450000
0"
#3475000
1&
b0 #
b0 $
b0 !
#3500000
1"
#3550000
0"
#3575000
0&
b10000 #
b10000 !
#3600000
1"
#3601000
b10000 $
#3650000
0"
#3675000
1&
b0 #
b0 $
b0 !
#3700000
1"
#3750000
0"
#3775000
0&
b10001 #
b10001 !
#3800000
1"
#3801000
b10001 $
#3850000
0"
#3875000
1&
b0 #
b0 $
b0 !
#3900000
1"
#3950000
0"
#3975000
0&
b10010 #
b10010 !
#4000000
1"
#4001000
b10010 $
#4050000
0"
#4075000
1&
b0 #
b0 $
b0 !
#4100000
1"
#4150000
0"
#4175000
0&
b10011 #
b10011 !
#4200000
1"
#4201000
b10011 $
#4250000
0"
#4275000
1&
b0 #
b0 $
b0 !
#4300000
1"
#4350000
0"
#4375000
0&
b10100 #
b10100 !
#4400000
1"
#4401000
b10100 $
#4450000
0"
#4475000
1&
b0 #
b0 $
b0 !
#4500000
1"
#4550000
0"
#4575000
0&
b10101 #
b10101 !
#4600000
1"
#4601000
b10101 $
#4650000
0"
#4675000
1&
b0 #
b0 $
b0 !
#4700000
1"
#4750000
0"
#4775000
0&
b10110 #
b10110 !
#4800000
1"
#4801000
b10110 $
#4850000
0"
#4875000
1&
b0 #
b0 $
b0 !
#4900000
1"
#4950000
0"
#4975000
0&
b10111 #
b10111 !
#5000000
1"
#5001000
b10111 $
#5050000
0"
#5075000
1&
b0 #
b0 $
b0 !
#5100000
1"
#5150000
0"
#5175000
0&
b11000 #
b11000 !
#5200000
1"
#5201000
b11000 $
#5250000
0"
#5275000
1&
b0 #
b0 $
b0 !
#5300000
1"
#5350000
0"
#5375000
0&
b11001 #
b11001 !
#5400000
1"
#5401000
b11001 $
#5450000
0"
#5475000
1&
b0 #
b0 $
b0 !
#5500000
1"
#5550000
0"
#5575000
0&
b11010 #
b11010 !
#5600000
1"
#5601000
b11010 $
#5650000
0"
#5675000
1&
b0 #
b0 $
b0 !
#5700000
1"
#5750000
0"
#5775000
0&
b11011 #
b11011 !
#5800000
1"
#5801000
b11011 $
#5850000
0"
#5875000
1&
b0 #
b0 $
b0 !
#5900000
1"
#5950000
0"
#5975000
0&
b11100 #
b11100 !
#6000000
1"
#6001000
b11100 $
#6050000
0"
#6075000
1&
b0 #
b0 $
b0 !
#6100000
1"
#6150000
0"
#6175000
0&
b11101 #
b11101 !
#6200000
1"
#6201000
b11101 $
#6250000
0"
#6275000
1&
b0 #
b0 $
b0 !
#6300000
1"
#6350000
0"
#6375000
0&
b11110 #
b11110 !
#6400000
1"
#6401000
b11110 $
#6450000
0"
#6475000
1&
b0 #
b0 $
b0 !
#6500000
1"
#6550000
0"
#6575000
0&
b11111 #
b11111 !
#6600000
1"
#6601000
b11111 $
#6650000
0"
#6675000
1&
b0 #
b0 $
b0 !
