lib/counter.v
module counter # (
	parameter WIDTH = 16
) (
	input clk,
	input rst_n,
	output reg [WIDTH-1:0] cnt
);

always @(posedge clk) begin
	if (rst_n == 0)
		cnt <= {WIDTH{1'b0}};
	else
		cnt <= cnt + 1;
end

endmodule

lib/counter_tb.v
`timescale 1ns/1ps

module counter_tb;
    parameter WIDTH     = 16;
    parameter FREQ      = 40_000;
    parameter PERIOD    = 1_000_000_000;

    reg                 clk;    // 40kHz
    reg                 rst_n;
    wire    [WIDTH-1:0] cnt;

    counter c0  (   .clk    (clk),
                    .rst_n   (rst_n),
                    .cnt    (cnt));
    initial begin            
        $dumpfile("counter.vcd");
        $dumpvars(0, counter_tb);
    end

    always #(500_000_000 / FREQ)
    // always #1
        clk     <= ~clk;

    initial begin
        clk         <= 1'b0;
        rst_n        <= 1'b0;

        #(1_000_000_000 / FREQ)  rst_n    <= 1'b1;

        #PERIOD $finish;
    end

endmodule

lib/counter.vcd
$date
	Fri Mar  4 08:59:18 2022
$end
$version
	Icarus Verilog
$end
$timescale
	1ps
$end
$scope module counter_tb $end
$var wire 16 ! cnt [15:0] $end
$var reg 1 " clk $end
$var reg 1 # rst_n $end
$scope module c0 $end
$var wire 1 " clk $end
$var wire 1 # rst_n $end
$var reg 16 $ cnt [15:0] $end
$upscope $end
$upscope $end
$enddefinitions $end
#0
$dumpvars
bx $
0#
0"
bx !
$end
#12500000
b0 !
b0 $
1"
#25000000
0"
1#
#37500000
b1 !
b1 $
1"
#50000000
0"
#62500000
b10 !
b10 $
1"
#75000000
0"
#87500000
b11 !
b11 $
1"
#100000000
0"
#112500000
b100 !
b100 $
1"
#125000000
0"
#137500000
b101 !
b101 $
1"
#150000000
0"
#162500000
b110 !
b110 $
1"
#175000000
0"
#187500000
b111 !
b111 $
1"
#200000000
0"
#212500000
b1000 !
b1000 $
1"
#225000000
0"
#237500000
b1001 !
b1001 $
1"
#250000000
0"
#262500000
b1010 !
b1010 $
1"
#275000000
0"
#287500000
b1011 !
b1011 $
1"
#300000000
0"
#312500000
b1100 !
b1100 $
1"
#325000000
0"
#337500000
b1101 !
b1101 $
1"
#350000000
0"
#362500000
b1110 !
b1110 $
1"
#375000000
0"
#387500000
b1111 !
b1111 $
1"
#400000000
0"
#412500000
b10000 !
b10000 $
1"
#425000000
0"
#437500000
b10001 !
b10001 $
1"
#450000000
0"
#462500000
b10010 !
b10010 $
1"
#475000000
0"
#487500000
b10011 !
b10011 $
1"
#500000000
0"
#512500000
b10100 !
b10100 $
1"
#525000000
0"
#537500000
b10101 !
b10101 $
1"
#550000000
0"
#562500000
b10110 !
b10110 $
1"
#575000000
0"
#587500000
b10111 !
b10111 $
1"
#600000000
0"
#612500000
b11000 !
b11000 $
1"
#625000000
0"
#637500000
b11001 !
b11001 $
1"
#650000000
0"
#662500000
b11010 !
b11010 $
1"
#675000000
0"
#687500000
b11011 !
b11011 $
1"
#700000000
0"
#712500000
b11100 !
b11100 $
1"
#725000000
0"
#737500000
b11101 !
b11101 $
1"
#750000000
0"
#762500000
b11110 !
b11110 $
1"
#775000000
0"
#787500000
b11111 !
b11111 $
1"
#800000000
0"
#812500000
b100000 !
b100000 $
1"
#825000000
0"
#837500000
b100001 !
b100001 $
1"
#850000000
0"
#862500000
b100010 !
b100010 $
1"
#875000000
0"
#887500000
b100011 !
b100011 $
1"
#900000000
0"
#912500000
b100100 !
b100100 $
1"
#925000000
0"
#937500000
b100101 !
b100101 $
1"
#950000000
0"
#962500000
b100110 !
b100110 $
1"
#975000000
0"
#987500000
b100111 !
b100111 $
1"
#1000000000
0"
#1012500000
b101000 !
b101000 $
1"
#1025000000
0"
#1037500000
b101001 !
b101001 $
1"
#1050000000
0"
#1062500000
b101010 !
b101010 $
1"
#1075000000
0"
#1087500000
b101011 !
b101011 $
1"
#1100000000
0"
#1112500000
b101100 !
b101100 $
1"
#1125000000
0"
#1137500000
b101101 !
b101101 $
1"
#1150000000
0"
#1162500000
b101110 !
b101110 $
1"
#1175000000
0"
#1187500000
b101111 !
b101111 $
1"
#1200000000
0"
#1212500000
b110000 !
b110000 $
1"
#1225000000
0"
#1237500000
b110001 !
b110001 $
1"
#1250000000
0"
#1262500000
b110010 !
b110010 $
1"
#1275000000
0"
#1287500000
b110011 !
b110011 $
1"
#1300000000
0"
#1312500000
b110100 !
b110100 $
1"
#1325000000
0"
#1337500000
b110101 !
b110101 $
1"
#1350000000
0"
#1362500000
b110110 !
b110110 $
1"
#1375000000
0"
#1387500000
b110111 !
b110111 $
1"
#1400000000
0"
#1412500000
b111000 !
b111000 $
1"
#1425000000
0"
#1437500000
b111001 !
b111001 $
1"
#1450000000
0"
#1462500000
b111010 !
b111010 $
1"
#1475000000
0"
#1487500000
b111011 !
b111011 $
1"
#1500000000
0"
#1512500000
b111100 !
b111100 $
1"
#1525000000
0"
#1537500000
b111101 !
b111101 $
1"
#1550000000
0"
#1562500000
b111110 !
b111110 $
1"
#1575000000
0"
#1587500000
b111111 !
b111111 $
1"
#1600000000
0"
#1612500000
b1000000 !
b1000000 $
1"
#1625000000
0"
#1637500000
b1000001 !
b1000001 $
1"
#1650000000
0"
#1662500000
b1000010 !
b1000010 $
1"
#1675000000
0"
#1687500000
b1000011 !
b1000011 $
1"
#1700000000
0"
#1712500000
b1000100 !
b1000100 $
1"
#1725000000
0"
#1737500000
b1000101 !
b1000101 $
1"
#1750000000
0"
#1762500000
b1000110 !
b1000110 $
1"
#1775000000
0"
#1787500000
b1000111 !
b1000111 $
1"
#1800000000
0"
#1812500000
b1001000 !
b1001000 $
1"
#1825000000
0"
#1837500000
b1001001 !
b1001001 $
1"
#1850000000
0"
#1862500000
b1001010 !
b1001010 $
1"
#1875000000
0"
#1887500000
b1001011 !
b1001011 $
1"
#1900000000
0"
#1912500000
b1001100 !
b1001100 $
1"
#1925000000
0"
#1937500000
b1001101 !
b1001101 $
1"
#1950000000
0"
#1962500000
b1001110 !
b1001110 $
1"
#1975000000
0"
#1987500000
b1001111 !
b1001111 $
1"
#2000000000
0"
#2012500000
b1010000 !
b1010000 $
1"
#2025000000
0"
#2037500000
b1010001 !
b1010001 $
1"
#2050000000
0"
#2062500000
b1010010 !
b1010010 $
1"
#2075000000
0"
#2087500000
b1010011 !
b1010011 $
1"
#2100000000
0"
#2112500000
b1010100 !
b1010100 $
1"
#2125000000
0"
#2137500000
b1010101 !
b1010101 $
1"
#2150000000
0"
#2162500000
b1010110 !
b1010110 $
1"
#2175000000
0"
#2187500000
b1010111 !
b1010111 $
1"
#2200000000
0"
#2212500000
b1011000 !
b1011000 $
1"
#2225000000
0"
#2237500000
b1011001 !
b1011001 $
1"
#2250000000
0"
#2262500000
b1011010 !
b1011010 $
1"
#2275000000
0"
#2287500000
b1011011 !
b1011011 $
1"
#2300000000
0"
#2312500000
b1011100 !
b1011100 $
1"
#2325000000
0"
#2337500000
b1011101 !
b1011101 $
1"
#2350000000
0"
#2362500000
b1011110 !
b1011110 $
1"
#2375000000
0"
#2387500000
b1011111 !
b1011111 $
1"
#2400000000
0"
#2412500000
b1100000 !
b1100000 $
1"
#2425000000
0"
#2437500000
b1100001 !
b1100001 $
1"
#2450000000
0"
#2462500000
b1100010 !
b1100010 $
1"
#2475000000
0"
#2487500000
b1100011 !
b1100011 $
1"
#2500000000
0"
#2512500000
b1100100 !
b1100100 $
1"
#2525000000
0"
#2537500000
b1100101 !
b1100101 $
1"
#2550000000
0"
#2562500000
b1100110 !
b1100110 $
1"
#2575000000
0"
#2587500000
b1100111 !
b1100111 $
1"
#2600000000
0"
#2612500000
b1101000 !
b1101000 $
1"
#2625000000
0"
#2637500000
b1101001 !
b1101001 $
1"
#2650000000
0"
#2662500000
b1101010 !
b1101010 $
1"
#2675000000
0"
#2687500000
b1101011 !
b1101011 $
1"
#2700000000
0"
#2712500000
b1101100 !
b1101100 $
1"
#2725000000
0"
#2737500000
b1101101 !
b1101101 $
1"
#2750000000
0"
#2762500000
b1101110 !
b1101110 $
1"
#2775000000
0"
#2787500000
b1101111 !
b1101111 $
1"
#2800000000
0"
#2812500000
b1110000 !
b1110000 $
1"
#2825000000
0"
#2837500000
b1110001 !
b1110001 $
1"
#2850000000
0"
#2862500000
b1110010 !
b1110010 $
1"
#2875000000
0"
#2887500000
b1110011 !
b1110011 $
1"
#2900000000
0"
#2912500000
b1110100 !
b1110100 $
1"
#2925000000
0"
#2937500000
b1110101 !
b1110101 $
1"
#2950000000
0"
#2962500000
b1110110 !
b1110110 $
1"
#2975000000
0"
#2987500000
b1110111 !
b1110111 $
1"
#3000000000
0"
#3012500000
b1111000 !
b1111000 $
1"
#3025000000
0"
#3037500000
b1111001 !
b1111001 $
1"
#3050000000
0"
#3062500000
b1111010 !
b1111010 $
1"
#3075000000
0"
#3087500000
b1111011 !
b1111011 $
1"
#3100000000
0"
#3112500000
b1111100 !
b1111100 $
1"
#3125000000
0"
#3137500000
b1111101 !
b1111101 $
1"
#3150000000
0"
#3162500000
b1111110 !
b1111110 $
1"
#3175000000
0"
#3187500000
b1111111 !
b1111111 $
1"
#3200000000
0"
#3212500000
b10000000 !
b10000000 $
1"
#3225000000
0"
#3237500000
b10000001 !
b10000001 $
1"
#3250000000
0"
#3262500000
b10000010 !
b10000010 $
1"
#3275000000
0"
#3287500000
b10000011 !
b10000011 $
1"
#3300000000
0"
#3312500000
b10000100 !
b10000100 $
1"
#3325000000
0"
#3337500000
b10000101 !
b10000101 $
1"
#3350000000
0"
#3362500000
b10000110 !
b10000110 $
1"
#3375000000
0"
#3387500000
b10000111 !
b10000111 $
1"
#3400000000
0"
#3412500000
b10001000 !
b10001000 $
1"
#3425000000
0"
#3437500000
b10001001 !
b10001001 $
1"
#3450000000
0"
#3462500000
b10001010 !
b10001010 $
1"
#3475000000
0"
#3487500000
b10001011 !
b10001011 $
1"
#3500000000
0"
#3512500000
b10001100 !
b10001100 $
1"
#3525000000
0"
#3537500000
b10001101 !
b10001101 $
1"
#3550000000
0"
#3562500000
b10001110 !
b10001110 $
1"
#3575000000
0"
#3587500000
b10001111 !
b10001111 $
1"
#3600000000
0"
#3612500000
b10010000 !
b10010000 $
1"
#3625000000
0"
#3637500000
b10010001 !
b10010001 $
1"
#3650000000
0"
#3662500000
b10010010 !
b10010010 $
1"
#3675000000
0"
#3687500000
b10010011 !
b10010011 $
1"
#3700000000
0"
#3712500000
b10010100 !
b10010100 $
1"
#3725000000
0"
#3737500000
b10010101 !
b10010101 $
1"
#3750000000
0"
#3762500000
b10010110 !
b10010110 $
1"
#3775000000
0"
#3787500000
b10010111 !
b10010111 $
1"
#3800000000
0"
#3812500000
b10011000 !
b10011000 $
1"
#3825000000
0"
#3837500000
b10011001 !
b10011001 $
1"
#3850000000
0"
#3862500000
b10011010 !
b10011010 $
1"
#3875000000
0"
#3887500000
b10011011 !
b10011011 $
1"
#3900000000
0"
#3912500000
b10011100 !
b10011100 $
1"
#3925000000
0"
#3937500000
b10011101 !
b10011101 $
1"
#3950000000
0"
#3962500000
b10011110 !
b10011110 $
1"
#3975000000
0"
#3987500000
b10011111 !
b10011111 $
1"
#4000000000
0"
#4012500000
b10100000 !
b10100000 $
1"
#4025000000
0"
#4037500000
b10100001 !
b10100001 $
1"
#4050000000
0"
#4062500000
b10100010 !
b10100010 $
1"
#4075000000
0"
#4087500000
b10100011 !
b10100011 $
1"
#4100000000
0"
#4112500000
b10100100 !
b10100100 $
1"
#4125000000
0"
#4137500000
b10100101 !
b10100101 $
1"
#4150000000
0"
#4162500000
b10100110 !
b10100110 $
1"
#4175000000
0"
#4187500000
b10100111 !
b10100111 $
1"
#4200000000
0"
#4212500000
b10101000 !
b10101000 $
1"
#4225000000
0"
#4237500000
b10101001 !
b10101001 $
1"
#4250000000
0"
#4262500000
b10101010 !
b10101010 $
1"
#4275000000
0"
#4287500000
b10101011 !
b10101011 $
1"
#4300000000
0"
#4312500000
b10101100 !
b10101100 $
1"
#4325000000
0"
#4337500000
b10101101 !
b10101101 $
1"
#4350000000
0"
#4362500000
b10101110 !
b10101110 $
1"
#4375000000
0"
#4387500000
b10101111 !
b10101111 $
1"
#4400000000
0"
#4412500000
b10110000 !
b10110000 $
1"
#4425000000
0"
#4437500000
b10110001 !
b10110001 $
1"
#4450000000
0"
#4462500000
b10110010 !
b10110010 $
1"
#4475000000
0"
#4487500000
b10110011 !
b10110011 $
1"
#4500000000
0"
#4512500000
b10110100 !
b10110100 $
1"
#4525000000
0"
#4537500000
b10110101 !
b10110101 $
1"
#4550000000
0"
#4562500000
b10110110 !
b10110110 $
1"
#4575000000
0"
#4587500000
b10110111 !
b10110111 $
1"
#4600000000
0"
#4612500000
b10111000 !
b10111000 $
1"
#4625000000
0"
#4637500000
b10111001 !
b10111001 $
1"
#4650000000
0"
#4662500000
b10111010 !
b10111010 $
1"
#4675000000
0"
#4687500000
b10111011 !
b10111011 $
1"
#4700000000
0"
#4712500000
b10111100 !
b10111100 $
1"
#4725000000
0"
#4737500000
b10111101 !
b10111101 $
1"
#4750000000
0"
#4762500000
b10111110 !
b10111110 $
1"
#4775000000
0"
#4787500000
b10111111 !
b10111111 $
1"
#4800000000
0"
#4812500000
b11000000 !
b11000000 $
1"
#4825000000
0"
#4837500000
b11000001 !
b11000001 $
1"
#4850000000
0"
#4862500000
b11000010 !
b11000010 $
1"
#4875000000
0"
#4887500000
b11000011 !
b11000011 $
1"
#4900000000
0"
#4912500000
b11000100 !
b11000100 $
1"
#4925000000
0"
#4937500000
b11000101 !
b11000101 $
1"
#4950000000
0"
#4962500000
b11000110 !
b11000110 $
1"
#4975000000
0"
#4987500000
b11000111 !
b11000111 $
1"
#5000000000
0"
#5012500000
b11001000 !
b11001000 $
1"
#5025000000
0"
#5037500000
b11001001 !
b11001001 $
1"
#5050000000
0"
#5062500000
b11001010 !
b11001010 $
1"
#5075000000
0"
#5087500000
b11001011 !
b11001011 $
1"
#5100000000
0"
#5112500000
b11001100 !
b11001100 $
1"
#5125000000
0"
#5137500000
b11001101 !
b11001101 $
1"
#5150000000
0"
#5162500000
b11001110 !
b11001110 $
1"
#5175000000
0"
#5187500000
b11001111 !
b11001111 $
1"
#5200000000
0"
#5212500000
b11010000 !
b11010000 $
1"
#5225000000
0"
#5237500000
b11010001 !
b11010001 $
1"
#5250000000
0"
#5262500000
b11010010 !
b11010010 $
1"
#5275000000
0"
#5287500000
b11010011 !
b11010011 $
1"
#5300000000
0"
#5312500000
b11010100 !
b11010100 $
1"
#5325000000
0"
#5337500000
b11010101 !
b11010101 $
1"
#5350000000
0"
#5362500000
b11010110 !
b11010110 $
1"
#5375000000
0"
#5387500000
b11010111 !
b11010111 $
1"
#5400000000
0"
#5412500000
b11011000 !
b11011000 $
1"
#5425000000
0"
#5437500000
b11011001 !
b11011001 $
1"
#5450000000
0"
#5462500000
b11011010 !
b11011010 $
1"
#5475000000
0"
#5487500000
b11011011 !
b11011011 $
1"
#5500000000
0"
#5512500000
b11011100 !
b11011100 $
1"
#5525000000
0"
#5537500000
b11011101 !
b11011101 $
1"
#5550000000
0"
#5562500000
b11011110 !
b11011110 $
1"
#5575000000
0"
#5587500000
b11011111 !
b11011111 $
1"
#5600000000
0"
#5612500000
b11100000 !
b11100000 $
1"
#5625000000
0"
#5637500000
b11100001 !
b11100001 $
1"
#5650000000
0"
#5662500000
b11100010 !
b11100010 $
1"
#5675000000
0"
#5687500000
b11100011 !
b11100011 $
1"
#5700000000
0"
#5712500000
b11100100 !
b11100100 $
1"
#5725000000
0"
#5737500000
b11100101 !
b11100101 $
1"
#5750000000
0"
#5762500000
b11100110 !
b11100110 $
1"
#5775000000
0"
#5787500000
b11100111 !
b11100111 $
1"
#5800000000
0"
#5812500000
b11101000 !
b11101000 $
1"
#5825000000
0"
#5837500000
b11101001 !
b11101001 $
1"
#5850000000
0"
#5862500000
b11101010 !
b11101010 $
1"
#5875000000
0"
#5887500000
b11101011 !
b11101011 $
1"
#5900000000
0"
#5912500000
b11101100 !
b11101100 $
1"
#5925000000
0"
#5937500000
b11101101 !
b11101101 $
1"
#5950000000
0"
#5962500000
b11101110 !
b11101110 $
1"
#5975000000
0"
#5987500000
b11101111 !
b11101111 $
1"
#6000000000
0"
#6012500000
b11110000 !
b11110000 $
1"
#6025000000
0"
#6037500000
b11110001 !
b11110001 $
1"
#6050000000
0"
#6062500000
b11110010 !
b11110010 $
1"
#6075000000
0"
#6087500000
b11110011 !
b11110011 $
1"
#6100000000
0"
#6112500000
b11110100 !
b11110100 $
1"
#6125000000
0"
#6137500000
b11110101 !
b11110101 $
1"
#6150000000
0"
#6162500000
b11110110 !
b11110110 $
1"
#6175000000
0"
#6187500000
b11110111 !
b11110111 $
1"
#6200000000
0"
#6212500000
b11111000 !
b11111000 $
1"
#6225000000
0"
#6237500000
b11111001 !
b11111001 $
1"
#6250000000
0"
#6262500000
b11111010 !
b11111010 $
1"
#6275000000
0"
#6287500000
b11111011 !
b11111011 $
1"
#6300000000
0"
#6312500000
b11111100 !
b11111100 $
1"
#6325000000
0"
#6337500000
b11111101 !
b11111101 $
1"
#6350000000
0"
#6362500000
b11111110 !
b11111110 $
1"
#6375000000
0"
#6387500000
b11111111 !
b11111111 $
1"
#6400000000
0"
#6412500000
b100000000 !
b100000000 $
1"
#6425000000
0"
#6437500000
b100000001 !
b100000001 $
1"
#6450000000
0"
#6462500000
b100000010 !
b100000010 $
1"
#6475000000
0"
#6487500000
b100000011 !
b100000011 $
1"
#6500000000
0"
#6512500000
b100000100 !
b100000100 $
1"
#6525000000
0"
#6537500000
b100000101 !
b100000101 $
1"
#6550000000
0"
#6562500000
b100000110 !
b100000110 $
1"
#6575000000
0"
#6587500000
b100000111 !
b100000111 $
1"
#6600000000
0"
#6612500000
b100001000 !
b100001000 $
1"
#6625000000
0"
#6637500000
b100001001 !
b100001001 $
1"
#6650000000
0"
#6662500000
b100001010 !
b100001010 $
1"
#6675000000
0"
#6687500000
b100001011 !
b100001011 $
1"
#6700000000
0"
#6712500000
b100001100 !
b100001100 $
1"
#6725000000
0"
#6737500000
b100001101 !
b100001101 $
1"
#6750000000
0"
#6762500000
b100001110 !
b100001110 $
1"
#6775000000
0"
#6787500000
b100001111 !
b100001111 $
1"
#6800000000
0"
#6812500000
b100010000 !
b100010000 $
1"
#6825000000
0"
#6837500000
b100010001 !
b100010001 $
1"
#6850000000
0"
#6862500000
b100010010 !
b100010010 $
1"
#6875000000
0"
#6887500000
b100010011 !
b100010011 $
1"
#6900000000
0"
#6912500000
b100010100 !
b100010100 $
1"
#6925000000
0"
#6937500000
b100010101 !
b100010101 $
1"
#6950000000
0"
#6962500000
b100010110 !
b100010110 $
1"
#6975000000
0"
#6987500000
b100010111 !
b100010111 $
1"
#7000000000
0"
#7012500000
b100011000 !
b100011000 $
1"
#7025000000
0"
#7037500000
b100011001 !
b100011001 $
1"
#7050000000
0"
#7062500000
b100011010 !
b100011010 $
1"
#7075000000
0"
#7087500000
b100011011 !
b100011011 $
1"
#7100000000
0"
#7112500000
b100011100 !
b100011100 $
1"
#7125000000
0"
#7137500000
b100011101 !
b100011101 $
1"
#7150000000
0"
#7162500000
b100011110 !
b100011110 $
1"
#7175000000
0"
#7187500000
b100011111 !
b100011111 $
1"
#7200000000
0"
#7212500000
b100100000 !
b100100000 $
1"
#7225000000
0"
#7237500000
b100100001 !
b100100001 $
1"
#7250000000
0"
#7262500000
b100100010 !
b100100010 $
1"
#7275000000
0"
#7287500000
b100100011 !
b100100011 $
1"
#7300000000
0"
#7312500000
b100100100 !
b100100100 $
1"
#7325000000
0"
#7337500000
b100100101 !
b100100101 $
1"
#7350000000
0"
#7362500000
b100100110 !
b100100110 $
1"
#7375000000
0"
#7387500000
b100100111 !
b100100111 $
1"
#7400000000
0"
#7412500000
b100101000 !
b100101000 $
1"
#7425000000
0"
#7437500000
b100101001 !
b100101001 $
1"
#7450000000
0"
#7462500000
b100101010 !
b100101010 $
1"
#7475000000
0"
#7487500000
b100101011 !
b100101011 $
1"
#7500000000
0"
#7512500000
b100101100 !
b100101100 $
1"
#7525000000
0"
#7537500000
b100101101 !
b100101101 $
1"
#7550000000
0"
#7562500000
b100101110 !
b100101110 $
1"
#7575000000
0"
#7587500000
b100101111 !
b100101111 $
1"
#7600000000
0"
#7612500000
b100110000 !
b100110000 $
1"
#7625000000
0"
#7637500000
b100110001 !
b100110001 $
1"
#7650000000
0"
#7662500000
b100110010 !
b100110010 $
1"
#7675000000
0"
#7687500000
b100110011 !
b100110011 $
1"
#7700000000
0"
#7712500000
b100110100 !
b100110100 $
1"
#7725000000
0"
#7737500000
b100110101 !
b100110101 $
1"
#7750000000
0"
#7762500000
b100110110 !
b100110110 $
1"
#7775000000
0"
#7787500000
b100110111 !
b100110111 $
1"
#7800000000
0"
#7812500000
b100111000 !
b100111000 $
1"
#7825000000
0"
#7837500000
b100111001 !
b100111001 $
1"
#7850000000
0"
#7862500000
b100111010 !
b100111010 $
1"
#7875000000
0"
#7887500000
b100111011 !
b100111011 $
1"
#7900000000
0"
#7912500000
b100111100 !
b100111100 $
1"
#7925000000
0"
#7937500000
b100111101 !
b100111101 $
1"
#7950000000
0"
#7962500000
b100111110 !
b100111110 $
1"
#7975000000
0"
#7987500000
b100111111 !
b100111111 $
1"
#8000000000
0"
#8012500000
b101000000 !
b101000000 $
1"
#8025000000
0"
#8037500000
b101000001 !
b101000001 $
1"
#8050000000
0"
#8062500000
b101000010 !
b101000010 $
1"
#8075000000
0"
#8087500000
b101000011 !
b101000011 $
1"
#8100000000
0"
#8112500000
b101000100 !
b101000100 $
1"
#8125000000
0"
#8137500000
b101000101 !
b101000101 $
1"
#8150000000
0"
#8162500000
b101000110 !
b101000110 $
1"
#8175000000
0"
#8187500000
b101000111 !
b101000111 $
1"
#8200000000
0"
#8212500000
b101001000 !
b101001000 $
1"
#8225000000
0"
#8237500000
b101001001 !
b101001001 $
1"
#8250000000
0"
#8262500000
b101001010 !
b101001010 $
1"
#8275000000
0"
#8287500000
b101001011 !
b101001011 $
1"
#8300000000
0"
#8312500000
b101001100 !
b101001100 $
1"
#8325000000
0"
#8337500000
b101001101 !
b101001101 $
1"
#8350000000
0"
#8362500000
b101001110 !
b101001110 $
1"
#8375000000
0"
#8387500000
b101001111 !
b101001111 $
1"
#8400000000
0"
#8412500000
b101010000 !
b101010000 $
1"
#8425000000
0"
#8437500000
b101010001 !
b101010001 $
1"
#8450000000
0"
#8462500000
b101010010 !
b101010010 $
1"
#8475000000
0"
#8487500000
b101010011 !
b101010011 $
1"
#8500000000
0"
#8512500000
b101010100 !
b101010100 $
1"
#8525000000
0"
#8537500000
b101010101 !
b101010101 $
1"
#8550000000
0"
#8562500000
b101010110 !
b101010110 $
1"
#8575000000
0"
#8587500000
b101010111 !
b101010111 $
1"
#8600000000
0"
#8612500000
b101011000 !
b101011000 $
1"
#8625000000
0"
#8637500000
b101011001 !
b101011001 $
1"
#8650000000
0"
#8662500000
b101011010 !
b101011010 $
1"
#8675000000
0"
#8687500000
b101011011 !
b101011011 $
1"
#8700000000
0"
#8712500000
b101011100 !
b101011100 $
1"
#8725000000
0"
#8737500000
b101011101 !
b101011101 $
1"
#8750000000
0"
#8762500000
b101011110 !
b101011110 $
1"
#8775000000
0"
#8787500000
b101011111 !
b101011111 $
1"
#8800000000
0"
#8812500000
b101100000 !
b101100000 $
1"
#8825000000
0"
#8837500000
b101100001 !
b101100001 $
1"
#8850000000
0"
#8862500000
b101100010 !
b101100010 $
1"
#8875000000
0"
#8887500000
b101100011 !
b101100011 $
1"
#8900000000
0"
#8912500000
b101100100 !
b101100100 $
1"
#8925000000
0"
#8937500000
b101100101 !
b101100101 $
1"
#8950000000
0"
#8962500000
b101100110 !
b101100110 $
1"
#8975000000
0"
#8987500000
b101100111 !
b101100111 $
1"
#9000000000
0"
#9012500000
b101101000 !
b101101000 $
1"
#9025000000
0"
#9037500000
b101101001 !
b101101001 $
1"
#9050000000
0"
#9062500000
b101101010 !
b101101010 $
1"
#9075000000
0"
#9087500000
b101101011 !
b101101011 $
1"
#9100000000
0"
#9112500000
b101101100 !
b101101100 $
1"
#9125000000
0"
#9137500000
b101101101 !
b101101101 $
1"
#9150000000
0"
#9162500000
b101101110 !
b101101110 $
1"
#9175000000
0"
#9187500000
b101101111 !
b101101111 $
1"
#9200000000
0"
#9212500000
b101110000 !
b101110000 $
1"
#9225000000
0"
#9237500000
b101110001 !
b101110001 $
1"
#9250000000
0"
#9262500000
b101110010 !
b101110010 $
1"
#9275000000
0"
#9287500000
b101110011 !
b101110011 $
1"
#9300000000
0"
#9312500000
b101110100 !
b101110100 $
1"
#9325000000
0"
#9337500000
b101110101 !
b101110101 $
1"
#9350000000
0"
#9362500000
b101110110 !
b101110110 $
1"
#9375000000
0"
#9387500000
b101110111 !
b101110111 $
1"
#9400000000
0"
#9412500000
b101111000 !
b101111000 $
1"
#9425000000
0"
#9437500000
b101111001 !
b101111001 $
1"
#9450000000
0"
#9462500000
b101111010 !
b101111010 $
1"
#9475000000
0"
#9487500000
b101111011 !
b101111011 $
1"
#9500000000
0"
#9512500000
b101111100 !
b101111100 $
1"
#9525000000
0"
#9537500000
b101111101 !
b101111101 $
1"
#9550000000
0"
#9562500000
b101111110 !
b101111110 $
1"
#9575000000
0"
#9587500000
b101111111 !
b101111111 $
1"
#9600000000
0"
#9612500000
b110000000 !
b110000000 $
1"
#9625000000
0"
#9637500000
b110000001 !
b110000001 $
1"
#9650000000
0"
#9662500000
b110000010 !
b110000010 $
1"
#9675000000
0"
#9687500000
b110000011 !
b110000011 $
1"
#9700000000
0"
#9712500000
b110000100 !
b110000100 $
1"
#9725000000
0"
#9737500000
b110000101 !
b110000101 $
1"
#9750000000
0"
#9762500000
b110000110 !
b110000110 $
1"
#9775000000
0"
#9787500000
b110000111 !
b110000111 $
1"
#9800000000
0"
#9812500000
b110001000 !
b110001000 $
1"
#9825000000
0"
#9837500000
b110001001 !
b110001001 $
1"
#9850000000
0"
#9862500000
b110001010 !
b110001010 $
1"
#9875000000
0"
#9887500000
b110001011 !
b110001011 $
1"
#9900000000
0"
#9912500000
b110001100 !
b110001100 $
1"
#9925000000
0"
#9937500000
b110001101 !
b110001101 $
1"
#9950000000
0"
#9962500000
b110001110 !
b110001110 $
1"
#9975000000
0"
#9987500000
b110001111 !
b110001111 $
1"
#10000000000
0"
#10012500000
b110010000 !
b110010000 $
1"
#10025000000
0"
#10037500000
b110010001 !
b110010001 $
1"
#10050000000
0"
#10062500000
b110010010 !
b110010010 $
1"
#10075000000
0"
#10087500000
b110010011 !
b110010011 $
1"
#10100000000
0"
#10112500000
b110010100 !
b110010100 $
1"
#10125000000
0"
#10137500000
b110010101 !
b110010101 $
1"
#10150000000
0"
#10162500000
b110010110 !
b110010110 $
1"
#10175000000
0"
#10187500000
b110010111 !
b110010111 $
1"
#10200000000
0"
#10212500000
b110011000 !
b110011000 $
1"
#10225000000
0"
#10237500000
b110011001 !
b110011001 $
1"
#10250000000
0"
#10262500000
b110011010 !
b110011010 $
1"
#10275000000
0"
#10287500000
b110011011 !
b110011011 $
1"
#10300000000
0"
#10312500000
b110011100 !
b110011100 $
1"
#10325000000
0"
#10337500000
b110011101 !
b110011101 $
1"
#10350000000
0"
#10362500000
b110011110 !
b110011110 $
1"
#10375000000
0"
#10387500000
b110011111 !
b110011111 $
1"
#10400000000
0"
#10412500000
b110100000 !
b110100000 $
1"
#10425000000
0"
#10437500000
b110100001 !
b110100001 $
1"
#10450000000
0"
#10462500000
b110100010 !
b110100010 $
1"
#10475000000
0"
#10487500000
b110100011 !
b110100011 $
1"
#10500000000
0"
#10512500000
b110100100 !
b110100100 $
1"
#10525000000
0"
#10537500000
b110100101 !
b110100101 $
1"
#10550000000
0"
#10562500000
b110100110 !
b110100110 $
1"
#10575000000
0"
#10587500000
b110100111 !
b110100111 $
1"
#10600000000
0"
#10612500000
b110101000 !
b110101000 $
1"
#10625000000
0"
#10637500000
b110101001 !
b110101001 $
1"
#10650000000
0"
#10662500000
b110101010 !
b110101010 $
1"
#10675000000
0"
#10687500000
b110101011 !
b110101011 $
1"
#10700000000
0"
#10712500000
b110101100 !
b110101100 $
1"
#10725000000
0"
#10737500000
b110101101 !
b110101101 $
1"
#10750000000
0"
#10762500000
b110101110 !
b110101110 $
1"
#10775000000
0"
#10787500000
b110101111 !
b110101111 $
1"
#10800000000
0"
#10812500000
b110110000 !
b110110000 $
1"
#10825000000
0"
#10837500000
b110110001 !
b110110001 $
1"
#10850000000
0"
#10862500000
b110110010 !
b110110010 $
1"
#10875000000
0"
#10887500000
b110110011 !
b110110011 $
1"
#10900000000
0"
#10912500000
b110110100 !
b110110100 $
1"
#10925000000
0"
#10937500000
b110110101 !
b110110101 $
1"
#10950000000
0"
#10962500000
b110110110 !
b110110110 $
1"
#10975000000
0"
#10987500000
b110110111 !
b110110111 $
1"
#11000000000
0"
#11012500000
b110111000 !
b110111000 $
1"
#11025000000
0"
#11037500000
b110111001 !
b110111001 $
1"
#11050000000
0"
#11062500000
b110111010 !
b110111010 $
1"
#11075000000
0"
#11087500000
b110111011 !
b110111011 $
1"
#11100000000
0"
#11112500000
b110111100 !
b110111100 $
1"
#11125000000
0"
#11137500000
b110111101 !
b110111101 $
1"
#11150000000
0"
#11162500000
b110111110 !
b110111110 $
1"
#11175000000
0"
#11187500000
b110111111 !
b110111111 $
1"
#11200000000
0"
#11212500000
b111000000 !
b111000000 $
1"
#11225000000
0"
#11237500000
b111000001 !
b111000001 $
1"
#11250000000
0"
#11262500000
b111000010 !
b111000010 $
1"
#11275000000
0"
#11287500000
b111000011 !
b111000011 $
1"
#11300000000
0"
#11312500000
b111000100 !
b111000100 $
1"
#11325000000
0"
